{
    "status":200,
    "data":[
        {
            "id":"wz_001",
            "title":"ES6标准入门——Lesson 1 let和const",
            "abstract":"ES6个人学习笔记之变量声明",
            "url":"let和const.md",
            "starts":5,
            "publish_date":"2019-10-10",
            "categories":["ES6"]
        },
        {
            "id":"wz_002",
            "title":"ES6标准入门——Lesson 2 变量的解构赋值",
            "abstract":"ES6个人学习笔记之解构",
            "url":"变量的解构赋值.md",
            "starts":5,
            "publish_date":"2019-10-11",
            "categories":["ES6","前端"]
        },
        {
            "id":"wz_003",
            "title":"ES6标准入门——lesson 3 Promise对象",
            "abstract":"ES6个人学习笔记之Promise",
            "publish_date":"2019-10-12",
            "url":"Promise对象.md",
            "categories":["ES6","学习"]
        }
    ]
}